[
  {
    "backcolor": "#ffffff",
    "name": "elephant42 Default-adjust"
  },
  [
    {
      "x": 3,
      "a": 7,
      "f": 2
    },
    "🔈",
    {
      "x": 9
    },
    "MWUp"
  ],
  [
    {
      "y": -0.75,
      "x": 2
    },
    "🔊",
    {
      "x": 11
    },
    "MWRt"
  ],
  [
    {
      "y": -0.75,
      "x": 4
    },
    "🔅",
    {
      "x": 7
    },
    "MWDn"
  ],
  [
    {
      "y": -0.75,
      "x": 5
    },
    "🔆",
    {
      "x": 5
    },
    "MWLeft"
  ],
  [
    {
      "y": -0.75,
      "x": 3
    },
    "🔈",
    {
      "x": 9
    },
    "MUp"
  ],
  [
    {
      "y": -0.875,
      "x": 1
    },
    "🔉",
    {
      "x": 13
    },
    "MAcl0"
  ],
  [
    {
      "y": -0.875,
      "x": 2
    },
    "🔊",
    {
      "x": 11
    },
    "MRt"
  ],
  [
    {
      "y": -0.75,
      "x": 4,
      "a": 4
    },
    "\n\n\n🔅\n\n\n\n\n\nSLock",
    {
      "x": 7,
      "a": 7
    },
    "MDn"
  ],
  [
    {
      "y": -0.875
    },
    "Reset",
    {
      "x": 15
    },
    ""
  ],
  [
    {
      "y": -0.875,
      "x": 5,
      "a": 4
    },
    "\n\n\n🔆\n\n\n\n\n\nPause",
    {
      "x": 5,
      "a": 7
    },
    "MLeft"
  ],
  [
    {
      "y": -0.75,
      "x": 3
    },
    "Insert",
    {
      "x": 9
    },
    "MBtn3"
  ],
  [
    {
      "y": -0.875,
      "x": 1
    },
    "🔉",
    {
      "x": 13
    },
    "MAcl1"
  ],
  [
    {
      "y": -0.875,
      "x": 2
    },
    "",
    {
      "x": 11
    },
    "MBtn4"
  ],
  [
    {
      "y": -0.75,
      "x": 4
    },
    "PrtScn",
    {
      "x": 7
    },
    "MBtn2"
  ],
  [
    {
      "y": -0.875
    },
    "EERst",
    {
      "x": 15
    },
    ""
  ],
  [
    {
      "y": -0.875,
      "x": 5
    },
    "NLock",
    {
      "x": 5
    },
    "MBtn1"
  ],
  [
    {
      "y": -0.625,
      "x": 1
    },
    "",
    {
      "x": 13
    },
    "MAcl2"
  ],
  [
    {
      "y": -0.375,
      "x": 3.25
    },
    "Alt",
    {
      "x": 8.5
    },
    "Bspc"
  ],
  [
    {
      "r": 15,
      "rx": 4.25,
      "ry": 4,
      "y": -0.25,
      "x": 0.25
    },
    "Cmd"
  ],
  [
    {
      "r": 30,
      "rx": 4.75,
      "ry": 4.125,
      "y": -0.375,
      "x": 1
    },
    "Space"
  ],
  [
    {
      "r": 45,
      "rx": 5.25,
      "ry": 4.25,
      "y": -0.5,
      "x": 1.75
    },
    "Shift"
  ],
  [
    {
      "r": -45,
      "rx": 11.75,
      "y": -0.5,
      "x": -2.75
    },
    "Del"
  ],
  [
    {
      "r": -30,
      "rx": 12.25,
      "ry": 4.125,
      "y": -0.375,
      "x": -2
    },
    "Space"
  ],
  [
    {
      "r": -15,
      "rx": 12.75,
      "ry": 4,
      "y": -0.25,
      "x": -1.25
    },
    "Enter"
  ]
]